evapro/__init__.py
evapro/config/__init__.py
evapro/config/conf.py
evapro/config/evapro.yaml
evapro/db/__init__.py
evapro/db/database.py
evapro/db/update_db.py
evapro/scripts/__init__.py
evapro/scripts/evaproject.py
evapro-1.3.0.dist-info/LICENSE
evapro-1.3.0.dist-info/METADATA
evapro-1.3.0.dist-info/WHEEL
evapro-1.3.0.dist-info/entry_points.txt
evapro-1.3.0.dist-info/RECORD
