Metadata-Version: 2.3
Name: evapro
Version: 1.3.0
Summary: 遍历lims数据库，把新下的lims任务单添加到anneva监控
License: MIT
Author: Yuan Zan
Author-email: yfinddream@gmail.com
Requires-Python: >=3.8.1,<4.0
Classifier: Development Status :: 3 - Alpha
Classifier: Intended Audience :: Developers
Classifier: License :: OSI Approved :: MIT License
Classifier: Operating System :: OS Independent
Classifier: Programming Language :: Python :: 3
Classifier: Programming Language :: Python :: 3.9
Classifier: Programming Language :: Python :: 3.10
Classifier: Programming Language :: Python :: 3.11
Classifier: Programming Language :: Python :: 3.12
Classifier: Programming Language :: Python :: 3.13
Classifier: Programming Language :: Python :: 3.8
Classifier: Topic :: Utilities
Requires-Dist: PyYAML (>=6.0,<7.0)
Requires-Dist: colorama (>=0.4.6,<0.5.0)
Requires-Dist: importlib-resources (>=5.12.0,<6.0.0)
Requires-Dist: pandas (>=2.0.0,<3.0.0)
Requires-Dist: pymysql (>=1.0.2,<2.0.0)
Project-URL: Documentation, https://github.com/seqyuan/evapro#readme
Project-URL: Homepage, https://github.com/seqyuan/evapro
Project-URL: Repository, https://github.com/seqyuan/evapro
